xmonkey_curator/__init__.py
xmonkey_curator/__version__.py
xmonkey_curator/base_handler.py
xmonkey_curator/file_utilities.py
xmonkey_curator/handler_registry.py
xmonkey_curator/lexer_utilities.py
xmonkey_curator/licenses_handler.py
xmonkey_curator/report_generator.py
xmonkey_curator/rules_handler.py
xmonkey_curator/scanner.py
xmonkey_curator/signatures_handler.py
xmonkey_curator/symbols_handler.py
xmonkey_curator/handlers/__init__.py
xmonkey_curator/handlers/archive_handler.py
xmonkey_curator/handlers/archivelib_handler.py
xmonkey_curator/handlers/cplus_handler.py
xmonkey_curator/handlers/elf_handler.py
xmonkey_curator/handlers/java_handler.py
xmonkey_curator/handlers/jvm_handler.py
xmonkey_curator/handlers/machos_handler.py
xmonkey_curator/handlers/objectivec_handler.py
xmonkey_curator/handlers/octetstream_handler.py
xmonkey_curator/handlers/perl_handler.py
xmonkey_curator/handlers/python_handler.py
xmonkey_curator/handlers/ruby_handler.py
xmonkey_curator/handlers/rust_handler.py
xmonkey_curator/handlers/sharedlib_handler.py
xmonkey_curator/handlers/text_handler.py
xmonkey_curator/licenses/__init__.py
xmonkey_curator/licenses/apache_2_0.json
xmonkey_curator/licenses/gpl_2_0.json
xmonkey_curator/licenses/gpl_3_0.json
xmonkey_curator/licenses/lgpl_2_1.json
xmonkey_curator/licenses/lgpl_3_0.json
xmonkey_curator/rules/__init__.py
xmonkey_curator/rules/license_files.json
xmonkey_curator/signatures/__init__.py
xmonkey_curator/signatures/ffmpeg.json
xmonkey_curator-0.1.18.dist-info/LICENSE
xmonkey_curator-0.1.18.dist-info/METADATA
xmonkey_curator-0.1.18.dist-info/WHEEL
xmonkey_curator-0.1.18.dist-info/entry_points.txt
xmonkey_curator-0.1.18.dist-info/top_level.txt
xmonkey_curator-0.1.18.dist-info/RECORD
