Metadata-Version: 2.1
Name: xmonkey-curator
Version: 0.1.18
Summary: Automated OSS curation scanner
Home-page: https://github.com/Xpertians/xmonkey-curator
Author: Oscar Valenzuela
Author-email: oscar.valenzuela.b@gmail.com
License: Apache 2.0
Classifier: Programming Language :: Python :: 3
Classifier: License :: OSI Approved :: Apache Software License
Classifier: Operating System :: OS Independent
Requires-Python: >=3.6
License-File: LICENSE
Requires-Dist: click >=7.0
Requires-Dist: lief >=0.11.5
Requires-Dist: python-magic
Requires-Dist: libmagic
Requires-Dist: pygments
Requires-Dist: ssdeep
Requires-Dist: tqdm
Requires-Dist: rpmfile
Requires-Dist: zstandard
Requires-Dist: requests
Requires-Dist: oslili
Requires-Dist: tabulate
Provides-Extra: test
Requires-Dist: pytest ; extra == 'test'
